{
  "packages": [
    {
      "repo": "WayfireWM/wayfire",
      "pkg": "wayfire-git",
      "sha": "a1f575701ab3ba41006a38c0a01f39d31fdf2dbb"
    },
    {
      "repo": "catchorg/catch2",
      "pkg": "catch2-git",
      "sha": "e8ba329b6c66b06c4afd07953020b74c4b0f1a75"
    },
    {
      "repo": "hyprwm/Hyprland",
      "pkg": "hyprland-git",
      "sha": "fdc847706a005dfaa204ad0cde0953abce3244bd"
    },
    {
      "repo": "Alexays/Waybar",
      "pkg": "waybar-hyprland-git",
      "sha": "ea38eec2afd249481df737cc38e055974f83967c"
    }
  ]
}
