{
  "packages": [
    {
      "repo": "WayfireWM/wayfire",
      "pkg": "wayfire-git",
      "sha": "a1f575701ab3ba41006a38c0a01f39d31fdf2dbb"
    },
    {
      "repo": "catchorg/catch2",
      "pkg": "catch2-git",
      "sha": "584973a485160bea0feb8764c28bb65d03b988ac"
    },
    {
      "repo": "hyprwm/Hyprland",
      "pkg": "hyprland-git",
      "sha": "431c74f111285eab41c17d724f335a324b5c833a"
    },
    {
      "repo": "Alexays/Waybar",
      "pkg": "waybar-hyprland-git",
      "sha": "ea38eec2afd249481df737cc38e055974f83967c"
    }
  ]
}
